MANIFEST.in
setup.py
entry/__init__.py
entry/entry.py
entry/store.py
entry/writer.py
entry/datatypes/__init__.py
entry/datatypes/digest.py
entry/representations/__init__.py
entry/representations/csv.py
entry/representations/json.py
entry/representations/primitive.py
entry/representations/tsv.py
entry/representations/txt.py
entry/representations/yaml.py
entry/stores/__init__.py
entry/stores/file.py
entry/stores/memory.py
entry/stores/mongodb.py
openregister_entry.egg-info/PKG-INFO
openregister_entry.egg-info/SOURCES.txt
openregister_entry.egg-info/dependency_links.txt
openregister_entry.egg-info/not-zip-safe
openregister_entry.egg-info/requires.txt
openregister_entry.egg-info/top_level.txt