Metadata-Version: 1.1
Name: openregister-entry
Version: 0.4.0
Summary: Entry model package
Home-page: https://github.com/openregister/entry
Author: Openregister.org
Author-email: paul.downey@whatfettle.com
License: MIT
Download-URL: https://github.com/openregister/entry
Platform: any
Classifier: Development Status :: 3 - Alpha
Classifier: Environment :: Web Environment
Classifier: Programming Language :: Python :: 3.4
